Workbook

Sheet Tables
A1: datasets | B1: credit risk | C1: bank customers | D1: FRED-QD | E1: FRED-MD
A2: potential target variable(s) | B2: =COUNTIFS('Column Type Key'!$A$2:$A$392,"credit risk",'Column Type Key'!$D$2:$D$392,"Y") -> 1 | C2: =COUNTIFS('Column Type Key'!$A$2:$A$392,"bank customers",'Column Type Key'!$D$2:$D$392,"Y") -> 0 | D2: =COUNTIFS('Column Type Key'!$A$2:$A$392,"FRED-QD",'Column Type Key'!$D$2:$D$392,"Y") -> 5 | E2: =COUNTIFS('Column Type Key'!$A$2:$A$392,"FRED-MD",'Column Type Key'!$D$2:$D$392,"Y") -> 4
A3: columns | B3: =COUNTIF('Column Type Key'!$A$2:$A$392,"credit risk") -> 12 | C3: =COUNTIF('Column Type Key'!$A$2:$A$392,"bank customers") -> 6 | D3: =COUNTIF('Column Type Key'!$A$2:$A$392,"FRED-QD") -> 246 | E3: =COUNTIF('Column Type Key'!$A$2:$A$392,"FRED-MD") -> 127
A4: row count | B4: 32581 | C4: 100 | D4: 269 | E4: 806
A5: Table 1 - A count of each dataset’s columns and row counts (yellow = fill in FRED row counts)
A7: types of variables | B7: credit risk | C7: bank customers | D7: FRED-QD | E7: FRED-MD
A8: discrete (binary) | B8: =COUNTIFS('Column Type Key'!$A$2:$A$392,"credit risk",'Column Type Key'!$C$2:$C$392,"discrete (binary)") -> 2 | C8: =COUNTIFS('Column Type Key'!$A$2:$A$392,"bank customers",'Column Type Key'!$C$2:$C$392,"discrete (binary)") -> 0 | D8: =COUNTIFS('Column Type Key'!$A$2:$A$392,"FRED-QD",'Column Type Key'!$C$2:$C$392,"discrete (binary)") -> 0 | E8: =COUNTIFS('Column Type Key'!$A$2:$A$392,"FRED-MD",'Column Type Key'!$C$2:$C$392,"discrete (binary)") -> 0
A9: discrete (integer) | B9: =COUNTIFS('Column Type Key'!$A$2:$A$392,"credit risk",'Column Type Key'!$C$2:$C$392,"discrete (integer)") -> 3 | C9: =COUNTIFS('Column Type Key'!$A$2:$A$392,"bank customers",'Column Type Key'!$C$2:$C$392,"discrete (integer)") -> 0 | D9: =COUNTIFS('Column Type Key'!$A$2:$A$392,"FRED-QD",'Column Type Key'!$C$2:$C$392,"discrete (integer)") -> 0 | E9: =COUNTIFS('Column Type Key'!$A$2:$A$392,"FRED-MD",'Column Type Key'!$C$2:$C$392,"discrete (integer)") -> 0
A10: numeric continuous | B10: =COUNTIFS('Column Type Key'!$A$2:$A$392,"credit risk",'Column Type Key'!$C$2:$C$392,"numeric continuous") -> 4 | C10: =COUNTIFS('Column Type Key'!$A$2:$A$392,"bank customers",'Column Type Key'!$C$2:$C$392,"numeric continuous") -> 0 | D10: =COUNTIFS('Column Type Key'!$A$2:$A$392,"FRED-QD",'Column Type Key'!$C$2:$C$392,"numeric continuous") -> 245 | E10: =COUNTIFS('Column Type Key'!$A$2:$A$392,"FRED-MD",'Column Type Key'!$C$2:$C$392,"numeric continuous") -> 126
A11: categorical (nominal) | B11: =COUNTIFS('Column Type Key'!$A$2:$A$392,"credit risk",'Column Type Key'!$C$2:$C$392,"categorical (nominal)") -> 2 | C11: =COUNTIFS('Column Type Key'!$A$2:$A$392,"bank customers",'Column Type Key'!$C$2:$C$392,"categorical (nominal)") -> 1 | D11: =COUNTIFS('Column Type Key'!$A$2:$A$392,"FRED-QD",'Column Type Key'!$C$2:$C$392,"categorical (nominal)") -> 0 | E11: =COUNTIFS('Column Type Key'!$A$2:$A$392,"FRED-MD",'Column Type Key'!$C$2:$C$392,"categorical (nominal)") -> 0
A12: categorical (ordinal) | B12: =COUNTIFS('Column Type Key'!$A$2:$A$392,"credit risk",'Column Type Key'!$C$2:$C$392,"categorical (ordinal)") -> 1 | C12: =COUNTIFS('Column Type Key'!$A$2:$A$392,"bank customers",'Column Type Key'!$C$2:$C$392,"categorical (ordinal)") -> 0 | D12: =COUNTIFS('Column Type Key'!$A$2:$A$392,"FRED-QD",'Column Type Key'!$C$2:$C$392,"categorical (ordinal)") -> 0 | E12: =COUNTIFS('Column Type Key'!$A$2:$A$392,"FRED-MD",'Column Type Key'!$C$2:$C$392,"categorical (ordinal)") -> 0
A13: identifier | B13: =COUNTIFS('Column Type Key'!$A$2:$A$392,"credit risk",'Column Type Key'!$C$2:$C$392,"identifier") -> 0 | C13: =COUNTIFS('Column Type Key'!$A$2:$A$392,"bank customers",'Column Type Key'!$C$2:$C$392,"identifier") -> 3 | D13: =COUNTIFS('Column Type Key'!$A$2:$A$392,"FRED-QD",'Column Type Key'!$C$2:$C$392,"identifier") -> 0 | E13: =COUNTIFS('Column Type Key'!$A$2:$A$392,"FRED-MD",'Column Type Key'!$C$2:$C$392,"identifier") -> 0
A14: date | B14: =COUNTIFS('Column Type Key'!$A$2:$A$392,"credit risk",'Column Type Key'!$C$2:$C$392,"date") -> 0 | C14: =COUNTIFS('Column Type Key'!$A$2:$A$392,"bank customers",'Column Type Key'!$C$2:$C$392,"date") -> 2 | D14: =COUNTIFS('Column Type Key'!$A$2:$A$392,"FRED-QD",'Column Type Key'!$C$2:$C$392,"date") -> 1 | E14: =COUNTIFS('Column Type Key'!$A$2:$A$392,"FRED-MD",'Column Type Key'!$C$2:$C$392,"date") -> 1
A15: total | B15: =SUM(B8:B14) -> 12 | C15: =SUM(C8:C14) -> 6 | D15: =SUM(D8:D14) -> 246 | E15: =SUM(E8:E14) -> 127
A16: Table 2 - The types of variables available in each dataset color coded for Table 3
A17: FRED target variables (red) are macro series related to the credit risk dataset. Delinquency/charge-off add-ons (closest to loan_status) are on the FRED Dictionary tab.
A19: credit risk | B19: bank customers | C19: FRED-QD | D19: FRED-MD
A20: person_age | B20: CustomerID | C20: sasdate | D20: sasdate
A21: person_income | B21: BirthDate | C21: GDPC1 | D21: RPI
A22: person_home_ownership | B22: SSN | C22: PCECC96 | D22: W875RX1
A23: person_emp_length | B23: AccountID | C23: PCDGx | D23: DPCERA3M086SBEA
A24: loan_intent | B24: AccountOpened | C24: PCESVx | D24: CMRMTSPLx
A25: loan_grade | B25: AccountType | C25: PCNDx | D25: RETAILx
A26: loan_amnt | C26: GPDIC1 | D26: INDPRO
A27: loan_int_rate | C27: FPIx | D27: IPFPNSS
A28: loan_status | C28: Y033RC1Q027SBEAx | D28: IPFINAL
A29: loan_percent_income | C29: PNFIx | D29: IPCONGD
A30: cb_person_default_on_file | C30: PRFIx | D30: IPDCONGD
A31: cb_person_cred_hist_length | C31: A014RE1Q156NBEA | D31: IPNCONGD
C32: GCEC1 | D32: IPBUSEQ
C33: A823RL1Q225SBEA | D33: IPMAT
C34: FGRECPTx | D34: IPDMAT
C35: SLCEx | D35: IPNMAT
C36: EXPGSC1 | D36: IPMANSICS
C37: IMPGSC1 | D37: IPB51222S
C38: DPIC96 | D38: IPFUELS
C39: OUTNFB | D39: CUMFNS
C40: OUTBS | D40: HWI
C41: OUTMS | D41: HWIURATIO
C42: INDPRO | D42: CLF16OV
C43: IPFINAL | D43: CE16OV
... C146: PPIIDC | D146: VIXCLSx
C147: WPSID61
C148: WPU0531
C149: WPU0561
C150: OILPRICEx
C151: AHETPIx
C152: CES2000000008x
C153: CES3000000008x
C154: COMPRMS
C155: COMPRNFB
C156: RCPHBS
C157: OPHMFG
C158: OPHNFB
... C265: S&P PE ratio
A266: Table 3 - Column names of each dataset, color coded by variable type (red italic = target variable)

Sheet FRED Dictionary
A1: dataset | B1: original name | C1: new name | D1: group | E1: description | F1: indicator timing | G1: timing basis | H1: variable type | I1: potential target? | J1: link to credit risk dataset | K1: data available (FRED)
A2: FRED-QD | B2: sasdate | C2: date | D2: Date | E2: Observation date (quarter start for QD, month start for MD) | F2: n/a | G2: Time index | H2: date
A3: FRED-QD | B3: GDPC1 | C3: gdp_real | D3: 1 - NIPA (output & income) | E3: Real Gross Domestic Product | F3: Coincident | G3: Moves with current activity (output, jobs, income, sales) | H3: numeric continuous
A4: FRED-QD | B4: PCECC96 | C4: pce_real | D4: 1 - NIPA (output & income) | E4: Real Personal Consumption Expenditures | F4: Coincident | G4: Moves with current activity (output, jobs, income, sales) | H4: numeric continuous
A5: FRED-QD | B5: PCDGx | C5: pce_durable | D5: 1 - NIPA (output & income) | E5: Real PCE: Durable Goods | F5: Coincident | G5: Moves with current activity (output, jobs, income, sales) | H5: numeric continuous
A6: FRED-QD | B6: PCESVx | C6: pce_services | D6: 1 - NIPA (output & income) | E6: Real PCE: Services | F6: Coincident | G6: Moves with current activity (output, jobs, income, sales) | H6: numeric continuous
A7: FRED-QD | B7: PCNDx | C7: pce_nondurable | D7: 1 - NIPA (output & income) | E7: Real PCE: Nondurable Goods | F7: Coincident | G7: Moves with current activity (output, jobs, income, sales) | H7: numeric continuous
A8: FRED-QD | B8: GPDIC1 | C8: invest_gross | D8: 1 - NIPA (output & income) | E8: Real Gross Private Domestic Investment | F8: Coincident | G8: Moves with current activity (output, jobs, income, sales) | H8: numeric continuous
A9: FRED-QD | B9: FPIx | C9: invest_fixed | D9: 1 - NIPA (output & income) | E9: Real Private Fixed Investment | F9: Coincident | G9: Moves with current activity (output, jobs, income, sales) | H9: numeric continuous
A10: FRED-QD | B10: Y033RC1Q027SBEAx | C10: invest_equip | D10: 1 - NIPA (output & income) | E10: Real Gross Private Domestic Investment: Nonresidential Equipment | F10: Coincident | G10: Moves with current activity (output, jobs, income, sales) | H10: numeric continuous
A11: FRED-QD | B11: PNFIx | C11: invest_nonres | D11: 1 - NIPA (output & income) | E11: Real Private Fixed Investment: Nonresidential | F11: Coincident | G11: Moves with current activity (output, jobs, income, sales) | H11: numeric continuous
A12: FRED-QD | B12: PRFIx | C12: invest_res | D12: 1 - NIPA (output & income) | E12: Real Private Fixed Investment: Residential | F12: Leading | G12: Residential investment typically turns first in a cycle | H12: numeric continuous
A13: FRED-QD | B13: A014RE1Q156NBEA | C13: invest_inv_chg | D13: 1 - NIPA (output & income) | E13: Shares of GDP: Change in Private Inventories | F13: Coincident | G13: Moves with current activity (output, jobs, income, sales) | H13: numeric continuous
... A184: FRED-QD | B184: BAA | C184: rate_corp_baa | D184: 8 - Interest Rates | E184: Moody's Seasoned Baa Corporate Bond Yield | F184: Leading | G184: Market yields reflect expected rates and risk | H184: numeric continuous
A185: FRED-QD | B185: BAA10YM | C185: spr_baa_10y | D185: 8 - Interest Rates | E185: Spread: Baa Corporate Yield minus 10-Year Treasury | F185: Leading | G185: Rate spreads / yield curve anticipate growth and credit stress | H185: numeric continuous | I185: Y | J185: Credit risk premium; moves with default risk and lending rates (loan_int_rate)
A186: FRED-QD | B186: MORTG10YRx | C186: spr_mort_10y | D186: 8 - Interest Rates | E186: Spread: 30-Year Mortgage Rate minus 10-Year Treasury | F186: Leading | G186: Rate spreads / yield curve anticipate growth and credit stress | H186: numeric continuous
A187: FRED-QD | B187: TB6M3Mx | C187: spr_6m_3m | D187: 8 - Interest Rates | E187: Spread: 6-Month minus 3-Month T-Bill | F187: Leading | G187: Rate spreads / yield curve anticipate growth and credit stress | H187: numeric continuous
A188: FRED-QD | B188: GS1TB3Mx | C188: spr_1y_3m | D188: 8 - Interest Rates | E188: Spread: 1-Year Treasury minus 3-Month T-Bill | F188: Leading | G188: Rate spreads / yield curve anticipate growth and credit stress | H188: numeric continuous
A189: FRED-QD | B189: GS10TB3Mx | C189: spr_10y_3m | D189: 8 - Interest Rates | E189: Spread: 10-Year Treasury minus 3-Month T-Bill | F189: Leading | G189: Rate spreads / yield curve anticipate growth and credit stress | H189: numeric continuous
A190: FRED-QD | B190: CPF3MTB3Mx | C190: spr_cp_tbill | D190: 8 - Interest Rates | E190: Spread: 3-Month Commercial Paper minus 3-Month T-Bill | F190: Leading | G190: Rate spreads / yield curve anticipate growth and credit stress | H190: numeric continuous
A191: FRED-QD | B191: GS5 | C191: rate_tsy_5y | D191: 8 - Interest Rates | E191: 5-Year Treasury Constant Maturity Rate | F191: Leading | G191: Market yields reflect expected rates and risk | H191: numeric continuous
A192: FRED-QD | B192: TB3SMFFM | C192: spr_3m_ff | D192: 8 - Interest Rates | E192: Spread: 3-Month T-Bill minus Fed Funds | F192: Leading | G192: Rate spreads / yield curve anticipate growth and credit stress | H192: numeric continuous
A193: FRED-QD | B193: T5YFFM | C193: spr_5y_ff | D193: 8 - Interest Rates | E193: Spread: 5-Year Treasury minus Fed Funds | F193: Leading | G193: Rate spreads / yield curve anticipate growth and credit stress | H193: numeric continuous
A194: FRED-QD | B194: AAAFFM | C194: spr_aaa_ff | D194: 8 - Interest Rates | E194: Spread: Moody's Aaa Corporate minus Fed Funds | F194: Leading | G194: Rate spreads / yield curve anticipate growth and credit stress | H194: numeric continuous
A195: FRED-QD | B195: CP3M | C195: rate_cp_3m | D195: 8 - Interest Rates | E195: 3-Month AA Financial Commercial Paper Rate | F195: Leading | G195: Market yields reflect expected rates and risk | H195: numeric continuous
A196: FRED-QD | B196: COMPAPFF | C196: spr_cp_ff | D196: 8 - Interest Rates | E196: Spread: 3-Month Commercial Paper minus Fed Funds | F196: Leading | G196: Rate spreads / yield curve anticipate growth and credit stress | H196: numeric continuous
A197: FRED-QD | B197: BOGMBASEREALx | C197: money_base_real | D197: 9 - Money & Credit | E197: Real Monetary Base | F197: Coincident | G197: Moves with current activity (output, jobs, income, sales) | H197: numeric continuous
... A201: FRED-QD | B201: CONSUMERx | C201: credit_cons_banks | D201: 9 - Money & Credit | E201: Real Consumer Loans at All Commercial Banks | F201: Lagging | G201: Loan balances respond after spending/income | H201: numeric continuous
A202: FRED-QD | B202: NONREVSLx | C202: credit_nonrevolving | D202: 9 - Money & Credit | E202: Real Nonrevolving Consumer Credit Outstanding | F202: Lagging | G202: Loan balances respond after spending/income | H202: numeric continuous | I202: Y | J202: Volume of nonrevolving consumer loans (personal/education/medical); ties to loan_amnt
A203: FRED-QD | B203: REALLNx | C203: credit_real_estate | D203: 9 - Money & Credit | E203: Real Real Estate Loans at All Commercial Banks | F203: Lagging | G203: Loan balances respond after spending/income | H203: numeric continuous
A204: FRED-QD | B204: REVOLSLx | C204: credit_revolving | D204: 9 - Money & Credit | E204: Real Revolving Consumer Credit Outstanding | F204: Lagging | G204: Loan balances respond after spending/income | H204: numeric continuous
A205: FRED-QD | B205: TOTALSLx | C205: credit_cons_total | D205: 9 - Money & Credit | E205: Real Total Consumer Credit Outstanding | F205: Lagging | G205: Loan balances respond after spending/income | H205: numeric continuous
A206: FRED-QD | B206: DRIWCIL | C206: credit_willing_cons | D206: 9 - Money & Credit | E206: Senior Loan Officer Survey: Net % of Banks More Willing to Make Consumer Installment Loans | F206: Leading | G206: Lender survey on upcoming credit supply | H206: numeric continuous | I206: Y | J206: Banks' willingness to make consumer installment loans; ties to approval/loan_grade
A207: FRED-QD | B207: TOTRESNS | C207: money_reserves | D207: 9 - Money & Credit | E207: Total Reserves of Depository Institutions | F207: Coincident | G207: Moves with current activity (output, jobs, income, sales) | H207: numeric continuous
A208: FRED-QD | B208: NONBORRES | C208: money_reserves_nb | D208: 9 - Money & Credit | E208: Nonborrowed Reserves of Depository Institutions | F208: Coincident | G208: Moves with current activity (output, jobs, income, sales) | H208: numeric continuous
A209: FRED-QD | B209: DTCOLNVHFNM | C209: credit_auto_loans | D209: 9 - Money & Credit | E209: Consumer Motor Vehicle Loans Outstanding (finance companies) | F209: Lagging | G209: Loan balances respond after spending/income | H209: numeric continuous
A210: FRED-QD | B210: DTCTHFNM | C210: credit_cons_fincos | D210: 9 - Money & Credit | E210: Total Consumer Loans & Leases Outstanding (finance companies) | F210: Lagging | G210: Loan balances respond after spending/income | H210: numeric continuous
A211: FRED-QD | B211: INVEST | C211: bank_securities | D211: 9 - Money & Credit | E211: Securities in Bank Credit at All Commercial Banks | F211: Lagging | G211: Loan balances respond after spending/income | H211: numeric continuous
A212: FRED-QD | B212: CONSPIx | C212: credit_to_income | D212: 9 - Money & Credit | E212: Nonrevolving Consumer Credit to Personal Income (ratio) | F212: Lagging | G212: Loan balances respond after spending/income | H212: numeric continuous | I212: Y | J212: Consumer credit-to-income ratio; macro analogue of loan_percent_income
A213: FRED-QD | B213: TABSHNOx | C213: hh_assets | D213: 10 - Household Balance Sheets | E213: Real Total Assets of Households & Nonprofits | F213: Lagging | G213: Balance sheets reflect accumulated past activity | H213: numeric continuous
A214: FRED-QD | B214: TLBSHNOx | C214: hh_liabilities | D214: 10 - Household Balance Sheets | E214: Real Total Liabilities of Households & Nonprofits | F214: Lagging | G214: Balance sheets reflect accumulated past activity | H214: numeric continuous
A215: FRED-QD | B215: LIABPIx | C215: hh_debt_to_income | D215: 10 - Household Balance Sheets | E215: Household Liabilities to Personal Income (ratio) | F215: Lagging | G215: Balance sheets reflect accumulated past activity | H215: numeric continuous | I215: Y | J215: Household debt-to-income; aggregate borrower leverage, like loan_percent_income
A216: FRED-QD | B216: TNWBSHNOx | C216: hh_net_worth | D216: 10 - Household Balance Sheets | E216: Real Net Worth of Households & Nonprofits | F216: Lagging | G216: Balance sheets reflect accumulated past activity | H216: numeric continuous
A217: FRED-QD | B217: NWPIx | C217: hh_nw_to_income | D217: 10 - Household Balance Sheets | E217: Household Net Worth to Personal Income (ratio) | F217: Lagging | G217: Balance sheets reflect accumulated past activity | H217: numeric continuous
A218: FRED-QD | B218: TARESAx | C218: hh_assets_ex_re | D218: 10 - Household Balance Sheets | E218: Real Household Assets excluding Real Estate | F218: Lagging | G218: Balance sheets reflect accumulated past activity | H218: numeric continuous
A219: FRED-QD | B219: HNOREMQ027Sx | C219: hh_real_estate | D219: 10 - Household Balance Sheets | E219: Real Household Real Estate Assets (market value) | F219: Lagging | G219: Balance sheets reflect accumulated past activity | H219: numeric continuous
A220: FRED-QD | B220: TFAABSHNOx | C220: hh_fin_assets | D220: 10 - Household Balance Sheets | E220: Real Total Financial Assets of Households & Nonprofits | F220: Lagging | G220: Balance sheets reflect accumulated past activity | H220: numeric continuous
A221: FRED-QD | B221: TWEXAFEGSMTHx | C221: fx_usd_broad | D221: 11 - Exchange Rates | E221: Trade-Weighted U.S. Dollar Index (broad) | F221: Coincident | G221: Moves with current activity (output, jobs, income, sales) | H221: numeric continuous
A222: FRED-QD | B222: EXUSEU | C222: fx_usd_eur | D222: 11 - Exchange Rates | E222: U.S. Dollars per Euro | F222: Coincident | G222: Moves with current activity (output, jobs, income, sales) | H222: numeric continuous
A223: FRED-QD | B223: EXSZUSx | C223: fx_chf_usd | D223: 11 - Exchange Rates | E223: Swiss Francs per U.S. Dollar | F223: Coincident | G223: Moves with current activity (output, jobs, income, sales) | H223: numeric continuous
A224: FRED-QD | B224: EXJPUSx | C224: fx_jpy_usd | D224: 11 - Exchange Rates | E224: Japanese Yen per U.S. Dollar | F224: Coincident | G224: Moves with current activity (output, jobs, income, sales) | H224: numeric continuous
A225: FRED-QD | B225: EXUSUKx | C225: fx_usd_gbp | D225: 11 - Exchange Rates | E225: U.S. Dollars per British Pound | F225: Coincident | G225: Moves with current activity (output, jobs, income, sales) | H225: numeric continuous
A226: FRED-QD | B226: EXCAUSx | C226: fx_cad_usd | D226: 11 - Exchange Rates | E226: Canadian Dollars per U.S. Dollar | F226: Coincident | G226: Moves with current activity (output, jobs, income, sales) | H226: numeric continuous
A227: FRED-QD | B227: UMCSENTx | C227: sent_consumer | D227: 12 - Other | E227: University of Michigan Consumer Sentiment | F227: Leading | G227: Survey/expectations measure | H227: numeric continuous
... A323: FRED-MD | B323: REALLN | C323: credit_real_estate | D323: 5 - Money & Credit | E323: Real Estate Loans at All Commercial Banks | F323: Lagging | G323: Loan balances respond after spending/income | H323: numeric continuous
A324: FRED-MD | B324: NONREVSL | C324: credit_nonrevolving | D324: 5 - Money & Credit | E324: Total Nonrevolving Consumer Credit Outstanding | F324: Lagging | G324: Loan balances respond after spending/income | H324: numeric continuous | I324: Y | J324: Volume of nonrevolving consumer loans (personal/education/medical); ties to loan_amnt
A325: FRED-MD | B325: CONSPI | C325: credit_to_income | D325: 5 - Money & Credit | E325: Nonrevolving Consumer Credit to Personal Income (ratio) | F325: Lagging | G325: Loan balances respond after spending/income | H325: numeric continuous | I325: Y | J325: Consumer credit-to-income ratio; macro analogue of loan_percent_income
A326: FRED-MD | B326: DTCOLNVHFNM | C326: credit_auto_loans | D326: 5 - Money & Credit | E326: Consumer Motor Vehicle Loans Outstanding (finance companies) | F326: Lagging | G326: Loan balances respond after spending/income | H326: numeric continuous
A327: FRED-MD | B327: DTCTHFNM | C327: credit_cons_fincos | D327: 5 - Money & Credit | E327: Total Consumer Loans & Leases Outstanding (finance companies) | F327: Lagging | G327: Loan balances respond after spending/income | H327: numeric continuous | I327: Y | J327: Total consumer loans & leases at finance companies; consumer borrowing demand
A328: FRED-MD | B328: INVEST | C328: bank_securities | D328: 5 - Money & Credit | E328: Securities in Bank Credit at All Commercial Banks | F328: Lagging | G328: Loan balances respond after spending/income | H328: numeric continuous
A329: FRED-MD | B329: FEDFUNDS | C329: rate_fedfunds | D329: 6 - Interest & Exchange Rates | E329: Effective Federal Funds Rate | F329: Lagging | G329: Fed policy reacts to past inflation/employment | H329: numeric continuous
A330: FRED-MD | B330: CP3Mx | C330: rate_cp_3m | D330: 6 - Interest & Exchange Rates | E330: 3-Month AA Financial Commercial Paper Rate | F330: Leading | G330: Market yields reflect expected rates and risk | H330: numeric continuous
A331: FRED-MD | B331: TB3MS | C331: rate_tbill_3m | D331: 6 - Interest & Exchange Rates | E331: 3-Month Treasury Bill Rate | F331: Coincident | G331: Short rates track current policy stance | H331: numeric continuous
A332: FRED-MD | B332: TB6MS | C332: rate_tbill_6m | D332: 6 - Interest & Exchange Rates | E332: 6-Month Treasury Bill Rate | F332: Coincident | G332: Short rates track current policy stance | H332: numeric continuous
A333: FRED-MD | B333: GS1 | C333: rate_tsy_1y | D333: 6 - Interest & Exchange Rates | E333: 1-Year Treasury Constant Maturity Rate | F333: Leading | G333: Market yields reflect expected rates and risk | H333: numeric continuous
A334: FRED-MD | B334: GS5 | C334: rate_tsy_5y | D334: 6 - Interest & Exchange Rates | E334: 5-Year Treasury Constant Maturity Rate | F334: Leading | G334: Market yields reflect expected rates and risk | H334: numeric continuous
A335: FRED-MD | B335: GS10 | C335: rate_tsy_10y | D335: 6 - Interest & Exchange Rates | E335: 10-Year Treasury Constant Maturity Rate | F335: Leading | G335: Market yields reflect expected rates and risk | H335: numeric continuous
A336: FRED-MD | B336: AAA | C336: rate_corp_aaa | D336: 6 - Interest & Exchange Rates | E336: Moody's Seasoned Aaa Corporate Bond Yield | F336: Leading | G336: Market yields reflect expected rates and risk | H336: numeric continuous
A337: FRED-MD | B337: BAA | C337: rate_corp_baa | D337: 6 - Interest & Exchange Rates | E337: Moody's Seasoned Baa Corporate Bond Yield | F337: Leading | G337: Market yields reflect expected rates and risk | H337: numeric continuous
A338: FRED-MD | B338: COMPAPFFx | C338: spr_cp_ff | D338: 6 - Interest & Exchange Rates | E338: Spread: 3-Month Commercial Paper minus Fed Funds | F338: Leading | G338: Rate spreads / yield curve anticipate growth and credit stress | H338: numeric continuous
A339: FRED-MD | B339: TB3SMFFM | C339: spr_3m_ff | D339: 6 - Interest & Exchange Rates | E339: Spread: 3-Month T-Bill minus Fed Funds | F339: Leading | G339: Rate spreads / yield curve anticipate growth and credit stress | H339: numeric continuous
... A344: FRED-MD | B344: AAAFFM | C344: spr_aaa_ff | D344: 6 - Interest & Exchange Rates | E344: Spread: Moody's Aaa Corporate minus Fed Funds | F344: Leading | G344: Rate spreads / yield curve anticipate growth and credit stress | H344: numeric continuous
A345: FRED-MD | B345: BAAFFM | C345: spr_baa_ff | D345: 6 - Interest & Exchange Rates | E345: Spread: Moody's Baa Corporate minus Fed Funds | F345: Leading | G345: Rate spreads / yield curve anticipate growth and credit stress | H345: numeric continuous | I345: Y | J345: Baa credit spread over Fed Funds; proxy for default risk premium (loan_int_rate)
A346: FRED-MD | B346: TWEXAFEGSMTHx | C346: fx_usd_broad | D346: 6 - Interest & Exchange Rates | E346: Trade-Weighted U.S. Dollar Index (broad) | F346: Coincident | G346: Moves with current activity (output, jobs, income, sales) | H346: numeric continuous
A347: FRED-MD | B347: EXSZUSx | C347: fx_chf_usd | D347: 6 - Interest & Exchange Rates | E347: Swiss Francs per U.S. Dollar | F347: Coincident | G347: Moves with current activity (output, jobs, income, sales) | H347: numeric continuous
A348: FRED-MD | B348: EXJPUSx | C348: fx_jpy_usd | D348: 6 - Interest & Exchange Rates | E348: Japanese Yen per U.S. Dollar | F348: Coincident | G348: Moves with current activity (output, jobs, income, sales) | H348: numeric continuous
A349: FRED-MD | B349: EXUSUKx | C349: fx_usd_gbp | D349: 6 - Interest & Exchange Rates | E349: U.S. Dollars per British Pound | F349: Coincident | G349: Moves with current activity (output, jobs, income, sales) | H349: numeric continuous
A350: FRED-MD | B350: EXCAUSx | C350: fx_cad_usd | D350: 6 - Interest & Exchange Rates | E350: Canadian Dollars per U.S. Dollar | F350: Coincident | G350: Moves with current activity (output, jobs, income, sales) | H350: numeric continuous
A351: FRED-MD | B351: WPSFD49207 | C351: ppi_finished | D351: 7 - Prices | E351: PPI: Finished Goods | F351: Lagging | G351: Inflation responds after demand changes | H351: numeric continuous
A352: FRED-MD | B352: WPSFD49502 | C352: ppi_fin_cons | D352: 7 - Prices | E352: PPI: Finished Consumer Goods | F352: Lagging | G352: Inflation responds after demand changes | H352: numeric continuous
A353: FRED-MD | B353: WPSID61 | C353: ppi_intermediate | D353: 7 - Prices | E353: PPI: Intermediate Materials | F353: Lagging | G353: Inflation responds after demand changes | H353: numeric continuous
A354: FRED-MD | B354: WPSID62 | C354: ppi_crude_mat | D354: 7 - Prices | E354: PPI: Crude Materials | F354: Leading | G354: Raw-material prices react early to demand | H354: numeric continuous
A355: FRED-MD | B355: OILPRICEx | C355: oil_price_real | D355: 7 - Prices | E355: Real Crude Oil Price (WTI) | F355: Leading | G355: Raw-material prices react early to demand | H355: numeric continuous
A356: FRED-MD | B356: PPICMM | C356: ppi_metals | D356: 7 - Prices | E356: PPI: Metals & Metal Products (Primary Nonferrous) | F356: Leading | G356: Raw-material prices react early to demand | H356: numeric continuous
A357: FRED-MD | B357: CPIAUCSL | C357: cpi_all | D357: 7 - Prices | E357: CPI: All Items | F357: Lagging | G357: Inflation responds after demand changes | H357: numeric continuous
... A374: FRED-MD | B374: VIXCLSx | C374: stk_vix | D374: 8 - Stock Market | E374: CBOE Volatility Index (VIX) | F374: Leading | G374: Markets price in expected future conditions | H374: numeric continuous
A375: FRED add-on | B375: DROCLACBS | C375: dq_other_cons | D375: Credit Performance (add-on) | E375: Delinquency Rate on Other Consumer Loans (non-credit-card), All Commercial Banks (%, SA) | F375: Lagging | G375: Defaults appear after borrowers are hit by a downturn | H375: numeric continuous | I375: Y | J375: Closest match to loan_status: share of installment loans (personal/education/medical-type) 30+ days past due | K375: Q1 1991 – present (quarterly)
A376: FRED add-on | B376: DRCLACBS | C376: dq_consumer | D376: Credit Performance (add-on) | E376: Delinquency Rate on Consumer Loans, All Commercial Banks (%, SA) | F376: Lagging | G376: Defaults appear after borrowers are hit by a downturn | H376: numeric continuous | I376: Y | J376: Share of all consumer loans past due; broader version of loan_status | K376: Q1 1987 – present (quarterly)
A377: FRED add-on | B377: COROCLACBS | C377: co_other_cons | D377: Credit Performance (add-on) | E377: Charge-Off Rate on Other Consumer Loans, All Commercial Banks (%, SA) | F377: Lagging | G377: Defaults appear after borrowers are hit by a downturn | H377: numeric continuous | I377: Y | J377: Share of installment loans written off as losses; closest to a true default | K377: Q1 1985 – present (quarterly)
A378: FRED add-on | B378: CORCACBS | C378: co_consumer | D378: Credit Performance (add-on) | E378: Charge-Off Rate on Consumer Loans, All Commercial Banks (%, SA) | F378: Lagging | G378: Defaults appear after borrowers are hit by a downturn | H378: numeric continuous | I378: Y | J378: Share of all consumer loans written off as losses | K378: Q1 1985 – present (quarterly)
A380: Groups follow the McCracken & Ng FRED-QD (14 groups) and FRED-MD (8 groups) appendices, so group numbers differ between QD and MD.
A381: A trailing "x" in an original name means McCracken & Ng adjusted/spliced the FRED series (often deflated to real terms).
A382: FRED add-on rows (yellow) are NOT in the QD/MD CSVs: download them from fred.stlouisfed.org and join on sasdate (quarterly, so they align with QD; for MD, repeat each quarter across its 3 months or aggregate MD to quarterly).
A383: Data availability: FRED-QD/MD start in 1959, but bank delinquency/charge-off rates only start 1985–1991, so a model using them as the target is limited to ~1985 onward (~160 quarters, or ~140 from 1991 for DROCLACBS).
A384: Long-history stand-ins back to 1959 that are already in QD/MD: BAA10YM / BAAFFM (default-risk spread) and UNRATE (main driver of consumer defaults).
A385: Indicator timing (conventional business-cycle classification, Conference Board/NBER style): Leading = tends to turn BEFORE the economy (useful as forecasting features); Coincident = moves WITH it; Lagging = turns AFTER it. Lagging series such as delinquency/charge-off rates make natural targets, and leading series are the best candidates to predict them.
A386: Time-series caution: when modeling, use lagged values (e.g. t-1, t-2) of features and a chronological train/test split, so no future information leaks into training.
A387: New-name prefixes: dq_ = delinquency rate, co_ = charge-off rate, px_ / cpi_ / ppi_ = prices, rate_ = interest rate, spr_ = rate spread, hh_ = household, nfc_ / nfnc_ = nonfinancial (non)corporate business, stk_ = stock market.

Sheet Column Type Key
A1: dataset | B1: column | C1: variable type | D1: target? (Y) | F1: Edit column C (type) or D (mark Y for target) here — Tables 1 and 2 recount automatically. Table 3 colors are static.
A2: credit risk | B2: person_age | C2: discrete (integer)
A3: credit risk | B3: person_income | C3: numeric continuous
A4: credit risk | B4: person_home_ownership | C4: categorical (nominal)
A5: credit risk | B5: person_emp_length | C5: discrete (integer)
A6: credit risk | B6: loan_intent | C6: categorical (nominal)
A7: credit risk | B7: loan_grade | C7: categorical (ordinal)
A8: credit risk | B8: loan_amnt | C8: numeric continuous
A9: credit risk | B9: loan_int_rate | C9: numeric continuous
A10: credit risk | B10: loan_status | C10: discrete (binary) | D10: Y
A11: credit risk | B11: loan_percent_income | C11: numeric continuous
A12: credit risk | B12: cb_person_default_on_file | C12: discrete (binary)
A13: credit risk | B13: cb_person_cred_hist_length | C13: discrete (integer)
A14: bank customers | B14: CustomerID | C14: identifier
A15: bank customers | B15: BirthDate | C15: date
A16: bank customers | B16: SSN | C16: identifier
A17: bank customers | B17: AccountID | C17: identifier
A18: bank customers | B18: AccountOpened | C18: date
A19: bank customers | B19: AccountType | C19: categorical (nominal)
A20: FRED-QD | B20: sasdate | C20: date
A21: FRED-QD | B21: GDPC1 | C21: numeric continuous
A22: FRED-QD | B22: PCECC96 | C22: numeric continuous
... A171: FRED-QD | B171: BAA | C171: numeric continuous
A172: FRED-QD | B172: BAA10YM | C172: numeric continuous | D172: Y
A173: FRED-QD | B173: MORTG10YRx | C173: numeric continuous
A174: FRED-QD | B174: TB6M3Mx | C174: numeric continuous
A175: FRED-QD | B175: GS1TB3Mx | C175: numeric continuous
A176: FRED-QD | B176: GS10TB3Mx | C176: numeric continuous
A177: FRED-QD | B177: CPF3MTB3Mx | C177: numeric continuous
A178: FRED-QD | B178: BOGMBASEREALx | C178: numeric continuous
A179: FRED-QD | B179: M1REAL | C179: numeric continuous
A180: FRED-QD | B180: M2REAL | C180: numeric continuous
A181: FRED-QD | B181: BUSLOANSx | C181: numeric continuous
A182: FRED-QD | B182: CONSUMERx | C182: numeric continuous
A183: FRED-QD | B183: NONREVSLx | C183: numeric continuous | D183: Y
A184: FRED-QD | B184: REALLNx | C184: numeric continuous
A185: FRED-QD | B185: REVOLSLx | C185: numeric continuous
A186: FRED-QD | B186: TOTALSLx | C186: numeric continuous
A187: FRED-QD | B187: DRIWCIL | C187: numeric continuous | D187: Y
A188: FRED-QD | B188: TABSHNOx | C188: numeric continuous
A189: FRED-QD | B189: TLBSHNOx | C189: numeric continuous
A190: FRED-QD | B190: LIABPIx | C190: numeric continuous | D190: Y
A191: FRED-QD | B191: TNWBSHNOx | C191: numeric continuous
A192: FRED-QD | B192: NWPIx | C192: numeric continuous
A193: FRED-QD | B193: TARESAx | C193: numeric continuous
A194: FRED-QD | B194: HNOREMQ027Sx | C194: numeric continuous
A195: FRED-QD | B195: TFAABSHNOx | C195: numeric continuous
A196: FRED-QD | B196: VIXCLSx | C196: numeric continuous
A197: FRED-QD | B197: USSTHPI | C197: numeric continuous
A198: FRED-QD | B198: SPCS10RSA | C198: numeric continuous
A199: FRED-QD | B199: SPCS20RSA | C199: numeric continuous
A200: FRED-QD | B200: TWEXAFEGSMTHx | C200: numeric continuous
A201: FRED-QD | B201: EXUSEU | C201: numeric continuous
A202: FRED-QD | B202: EXSZUSx | C202: numeric continuous
... A241: FRED-QD | B241: ISRATIOx | C241: numeric continuous
A242: FRED-QD | B242: CONSPIx | C242: numeric continuous | D242: Y
A243: FRED-QD | B243: CP3M | C243: numeric continuous
A244: FRED-QD | B244: COMPAPFF | C244: numeric continuous
A245: FRED-QD | B245: PERMITNE | C245: numeric continuous
A246: FRED-QD | B246: PERMITMW | C246: numeric continuous
A247: FRED-QD | B247: PERMITS | C247: numeric continuous
A248: FRED-QD | B248: PERMITW | C248: numeric continuous
A249: FRED-QD | B249: NIKKEI225 | C249: numeric continuous
A250: FRED-QD | B250: NASDAQCOM | C250: numeric continuous
A251: FRED-QD | B251: CUSR0000SEHC | C251: numeric continuous
A252: FRED-QD | B252: TLBSNNCBx | C252: numeric continuous
A253: FRED-QD | B253: TLBSNNCBBDIx | C253: numeric continuous
A254: FRED-QD | B254: TTAABSNNCBx | C254: numeric continuous
... A337: FRED-MD | B337: REALLN | C337: numeric continuous
A338: FRED-MD | B338: NONREVSL | C338: numeric continuous | D338: Y
A339: FRED-MD | B339: CONSPI | C339: numeric continuous | D339: Y
A340: FRED-MD | B340: S&P 500 | C340: numeric continuous
A341: FRED-MD | B341: S&P div yield | C341: numeric continuous
A342: FRED-MD | B342: S&P PE ratio | C342: numeric continuous
A343: FRED-MD | B343: FEDFUNDS | C343: numeric continuous
A344: FRED-MD | B344: CP3Mx | C344: numeric continuous
A345: FRED-MD | B345: TB3MS | C345: numeric continuous
A346: FRED-MD | B346: TB6MS | C346: numeric continuous
A347: FRED-MD | B347: GS1 | C347: numeric continuous
A348: FRED-MD | B348: GS5 | C348: numeric continuous
A349: FRED-MD | B349: GS10 | C349: numeric continuous
A350: FRED-MD | B350: AAA | C350: numeric continuous
A351: FRED-MD | B351: BAA | C351: numeric continuous
... A358: FRED-MD | B358: AAAFFM | C358: numeric continuous
A359: FRED-MD | B359: BAAFFM | C359: numeric continuous | D359: Y
A360: FRED-MD | B360: TWEXAFEGSMTHx | C360: numeric continuous
A361: FRED-MD | B361: EXSZUSx | C361: numeric continuous
A362: FRED-MD | B362: EXJPUSx | C362: numeric continuous
A363: FRED-MD | B363: EXUSUKx | C363: numeric continuous
A364: FRED-MD | B364: EXCAUSx | C364: numeric continuous
A365: FRED-MD | B365: WPSFD49207 | C365: numeric continuous
A366: FRED-MD | B366: WPSFD49502 | C366: numeric continuous
A367: FRED-MD | B367: WPSID61 | C367: numeric continuous
A368: FRED-MD | B368: WPSID62 | C368: numeric continuous
A369: FRED-MD | B369: OILPRICEx | C369: numeric continuous
A370: FRED-MD | B370: PPICMM | C370: numeric continuous
A371: FRED-MD | B371: CPIAUCSL | C371: numeric continuous
... A389: FRED-MD | B389: DTCOLNVHFNM | C389: numeric continuous
A390: FRED-MD | B390: DTCTHFNM | C390: numeric continuous | D390: Y
A391: FRED-MD | B391: INVEST | C391: numeric continuous
...
